lcmodel_wrapper/__init__.py
lcmodel_wrapper/pylcmodel.py
lcmodel_wrapper-0.1.2.dist-info/METADATA
lcmodel_wrapper-0.1.2.dist-info/WHEEL
lcmodel_wrapper-0.1.2.dist-info/top_level.txt
lcmodel_wrapper-0.1.2.dist-info/RECORD
