Metadata-Version: 2.4
Name: lcmodel_wrapper
Version: 0.1.2
Summary: Python wrapper for LCModel MRS fitting
Author-email: Julian Merkofer <j.p.merkofer@tue.nl>
License: MIT
Project-URL: Homepage, https://github.com/julianmer/PyLCModel
Project-URL: Repository, https://github.com/julianmer/PyLCModel
Requires-Python: >=3.8
Requires-Dist: numpy>=1.22
Requires-Dist: scipy>=1.10
Requires-Dist: fsl_mrs>=2.1.0
